{
	"data": [
		{
			"json_featuretype": "BusinessOwners",
			"First": "Dane",
			"Last Name": "Duran",
			"Company": "Purus Industries",
			"License Number": "FB1BE4",
			"Longitude": -123.100830898,
			"Latitude": 49.2467130235,
			"json_ogc_wkt_crs": "GEOGCS[\"WGS 84\",DATUM[\"WGS_1984\",SPHEROID[\"WGS 84\",6378137,298.257223563,AUTHORITY[\"EPSG\",\"7030\"]],AUTHORITY[\"EPSG\",\"6326\"]],PRIMEM[\"Greenwich\",0,AUTHORITY[\"EPSG\",\"8901\"]],UNIT[\"degree\",0.0174532925199433,AUTHORITY[\"EPSG\",\"9122\"]],AUTHORITY[\"EPSG\",\"4326\"]]",
			"json_geometry": {
				"type": "Point",
				"coordinates": [
					-123.100830898,
					49.2467130235
				]
			}
		},
		{
			"json_featuretype": "BusinessOwners",
			"First": "Amy",
			"Last Name": "Buckner",
			"Company": "Donec Nibh Quisque Institute",
			"License Number": "2DF78E",
			"Longitude": -123.1181531903,
			"Latitude": 49.27391626104,
			"json_ogc_wkt_crs": "GEOGCS[\"WGS 84\",DATUM[\"WGS_1984\",SPHEROID[\"WGS 84\",6378137,298.257223563,AUTHORITY[\"EPSG\",\"7030\"]],AUTHORITY[\"EPSG\",\"6326\"]],PRIMEM[\"Greenwich\",0,AUTHORITY[\"EPSG\",\"8901\"]],UNIT[\"degree\",0.0174532925199433,AUTHORITY[\"EPSG\",\"9122\"]],AUTHORITY[\"EPSG\",\"4326\"]]",
			"json_geometry": {
				"type": "Point",
				"coordinates": [
					-123.1181531903,
					49.273916261
				]
			}
		},
		{
			"json_featuretype": "BusinessOwners",
			"First": "Dominic",
			"Last Name": "Cobb",
			"Company": "Eleifend Nec Foundation",
			"License Number": "70E35F",
			"Longitude": -123.175102742,
			"Latitude": 49.26392632405,
			"json_ogc_wkt_crs": "GEOGCS[\"WGS 84\",DATUM[\"WGS_1984\",SPHEROID[\"WGS 84\",6378137,298.257223563,AUTHORITY[\"EPSG\",\"7030\"]],AUTHORITY[\"EPSG\",\"6326\"]],PRIMEM[\"Greenwich\",0,AUTHORITY[\"EPSG\",\"8901\"]],UNIT[\"degree\",0.0174532925199433,AUTHORITY[\"EPSG\",\"9122\"]],AUTHORITY[\"EPSG\",\"4326\"]]",
			"json_geometry": {
				"type": "Point",
				"coordinates": [
					-123.175102742,
					49.263926324
				]
			}
		},
		{
			"json_featuretype": "BusinessOwners",
			"First": "Chaim",
			"Last Name": "Mullins",
			"Company": "Enim Limited",
			"License Number": "AA0C69",
			"Longitude": -123.1311260189,
			"Latitude": 49.28068881119,
			"json_ogc_wkt_crs": "GEOGCS[\"WGS 84\",DATUM[\"WGS_1984\",SPHEROID[\"WGS 84\",6378137,298.257223563,AUTHORITY[\"EPSG\",\"7030\"]],AUTHORITY[\"EPSG\",\"6326\"]],PRIMEM[\"Greenwich\",0,AUTHORITY[\"EPSG\",\"8901\"]],UNIT[\"degree\",0.0174532925199433,AUTHORITY[\"EPSG\",\"9122\"]],AUTHORITY[\"EPSG\",\"4326\"]]",
			"json_geometry": {
				"type": "Point",
				"coordinates": [
					-123.1311260189,
					49.2806888112
				]
			}
		},
		{
			"json_featuretype": "BusinessOwners",
			"First": "Hedley",
			"Last Name": "Carey",
			"Company": "Lobortis Ltd",
			"License Number": "631E0C",
			"Longitude": -123.1310423863,
			"Latitude": 49.28898242048,
			"json_ogc_wkt_crs": "GEOGCS[\"WGS 84\",DATUM[\"WGS_1984\",SPHEROID[\"WGS 84\",6378137,298.257223563,AUTHORITY[\"EPSG\",\"7030\"]],AUTHORITY[\"EPSG\",\"6326\"]],PRIMEM[\"Greenwich\",0,AUTHORITY[\"EPSG\",\"8901\"]],UNIT[\"degree\",0.0174532925199433,AUTHORITY[\"EPSG\",\"9122\"]],AUTHORITY[\"EPSG\",\"4326\"]]",
			"json_geometry": {
				"type": "Point",
				"coordinates": [
					-123.1310423863,
					49.2889824205
				]
			}
		},
		{
			"json_featuretype": "BusinessOwners",
			"First": "Deanna",
			"Last Name": "Mathews",
			"Company": "Congue Corp.",
			"License Number": "C9F9B2",
			"Longitude": -123.0946014706,
			"Latitude": 49.27225868553,
			"json_ogc_wkt_crs": "GEOGCS[\"WGS 84\",DATUM[\"WGS_1984\",SPHEROID[\"WGS 84\",6378137,298.257223563,AUTHORITY[\"EPSG\",\"7030\"]],AUTHORITY[\"EPSG\",\"6326\"]],PRIMEM[\"Greenwich\",0,AUTHORITY[\"EPSG\",\"8901\"]],UNIT[\"degree\",0.0174532925199433,AUTHORITY[\"EPSG\",\"9122\"]],AUTHORITY[\"EPSG\",\"4326\"]]",
			"json_geometry": {
				"type": "Point",
				"coordinates": [
					-123.0946014706,
					49.2722586855
				]
			}
		},
		{
			"json_featuretype": "BusinessOwners",
			"First": "Valentine",
			"Last Name": "Wise",
			"Company": "Mattis Corp.",
			"License Number": "4C6F33",
			"Longitude": -123.1547154439,
			"Latitude": 49.26354092325,
			"json_ogc_wkt_crs": "GEOGCS[\"WGS 84\",DATUM[\"WGS_1984\",SPHEROID[\"WGS 84\",6378137,298.257223563,AUTHORITY[\"EPSG\",\"7030\"]],AUTHORITY[\"EPSG\",\"6326\"]],PRIMEM[\"Greenwich\",0,AUTHORITY[\"EPSG\",\"8901\"]],UNIT[\"degree\",0.0174532925199433,AUTHORITY[\"EPSG\",\"9122\"]],AUTHORITY[\"EPSG\",\"4326\"]]",
			"json_geometry": {
				"type": "Point",
				"coordinates": [
					-123.1547154439,
					49.2635409232
				]
			}
		},
		{
			"json_featuretype": "BusinessOwners",
			"First": "Curran",
			"Last Name": "Foreman",
			"Company": "Porta LLC",
			"License Number": "F572D7",
			"Longitude": -123.1176399316,
			"Latitude": 49.27934015336,
			"json_ogc_wkt_crs": "GEOGCS[\"WGS 84\",DATUM[\"WGS_1984\",SPHEROID[\"WGS 84\",6378137,298.257223563,AUTHORITY[\"EPSG\",\"7030\"]],AUTHORITY[\"EPSG\",\"6326\"]],PRIMEM[\"Greenwich\",0,AUTHORITY[\"EPSG\",\"8901\"]],UNIT[\"degree\",0.0174532925199433,AUTHORITY[\"EPSG\",\"9122\"]],AUTHORITY[\"EPSG\",\"4326\"]]",
			"json_geometry": {
				"type": "Point",
				"coordinates": [
					-123.1176399316,
					49.2793401534
				]
			}
		},
		{
			"json_featuretype": "BusinessOwners",
			"First": "Gavin",
			"Last Name": "Walker",
			"Company": "Lectus Consulting",
			"License Number": "0AAEDA",
			"Longitude": -123.0944534872,
			"Latitude": 49.26745768384,
			"json_ogc_wkt_crs": "GEOGCS[\"WGS 84\",DATUM[\"WGS_1984\",SPHEROID[\"WGS 84\",6378137,298.257223563,AUTHORITY[\"EPSG\",\"7030\"]],AUTHORITY[\"EPSG\",\"6326\"]],PRIMEM[\"Greenwich\",0,AUTHORITY[\"EPSG\",\"8901\"]],UNIT[\"degree\",0.0174532925199433,AUTHORITY[\"EPSG\",\"9122\"]],AUTHORITY[\"EPSG\",\"4326\"]]",
			"json_geometry": {
				"type": "Point",
				"coordinates": [
					-123.0944534872,
					49.2674576838
				]
			}
		},
		{
			"json_featuretype": "BusinessOwners",
			"First": "Jolene",
			"Last Name": "Eaton",
			"Company": "Turpis Egestas Aliquam Associates",
			"License Number": "DBE4CB",
			"Longitude": -123.1643602132,
			"Latitude": 49.26430630302,
			"json_ogc_wkt_crs": "GEOGCS[\"WGS 84\",DATUM[\"WGS_1984\",SPHEROID[\"WGS 84\",6378137,298.257223563,AUTHORITY[\"EPSG\",\"7030\"]],AUTHORITY[\"EPSG\",\"6326\"]],PRIMEM[\"Greenwich\",0,AUTHORITY[\"EPSG\",\"8901\"]],UNIT[\"degree\",0.0174532925199433,AUTHORITY[\"EPSG\",\"9122\"]],AUTHORITY[\"EPSG\",\"4326\"]]",
			"json_geometry": {
				"type": "Point",
				"coordinates": [
					-123.1643602132,
					49.264306303
				]
			}
		}
	],
	"total": 10,
	"next": "https://s3.amazonaws.com/FMEData/FMEData/Data/Planning/owners7.json"
}